[
  {
    "id": "basic",
    "name": "Basic",
    "requiredRelations": [
      "name"
    ]
  },
  {
    "id": "set",
    "name": "Set",
    "requiredRelations": [
      "setOf",
      "name"
    ]
  },
  {
    "id": "database",
    "name": "Database"
  },
  {
    "id": "relation",
    "name": "Relation"
  },
  {
    "id": "file",
    "name": "File"
  },
  {
    "id": "dashboard",
    "name": "Dashboard"
  },
  {
    "id": "todo",
    "name": "to-do",
    "requiredRelations": [
      "done",
      "name"
    ]
  },
  {
    "id": "space",
    "name": "Space"
  },
  {
    "id": "image",
    "name": "Image",
    "requiredRelations": [
      "iconImage"
    ]
  },
  {
    "id": "profile",
    "name": "Profile",
    "requiredRelations": [
      "name"
    ]
  },
  {
    "id": "objectType",
    "name": "Object Type",
    "requiredRelations": [
      "name",
      "recommendedRelations"
    ]
  }
]